amqpstorm/__init__.py
amqpstorm/base.py
amqpstorm/basic.py
amqpstorm/channel.py
amqpstorm/channel0.py
amqpstorm/compatibility.py
amqpstorm/connection.py
amqpstorm/exception.py
amqpstorm/exchange.py
amqpstorm/heartbeat.py
amqpstorm/io.py
amqpstorm/message.py
amqpstorm/queue.py
amqpstorm/rpc.py
amqpstorm/tx.py
amqpstorm/uri_connection.py
amqpstorm/management/__init__.py
amqpstorm/management/api.py
amqpstorm/management/base.py
amqpstorm/management/basic.py
amqpstorm/management/channel.py
amqpstorm/management/connection.py
amqpstorm/management/exception.py
amqpstorm/management/exchange.py
amqpstorm/management/healthchecks.py
amqpstorm/management/http_client.py
amqpstorm/management/queue.py
amqpstorm/management/user.py
amqpstorm/management/virtual_host.py
amqpstorm/tests/__init__.py
amqpstorm/tests/utility.py
amqpstorm/tests/functional/__init__.py
amqpstorm/tests/functional/test_basic.py
amqpstorm/tests/functional/test_exchange.py
amqpstorm/tests/functional/test_generic.py
amqpstorm/tests/functional/test_legacy.py
amqpstorm/tests/functional/test_queue.py
amqpstorm/tests/functional/test_reliability.py
amqpstorm/tests/functional/test_tx.py
amqpstorm/tests/functional/test_web_based.py
amqpstorm/tests/functional/utility.py
amqpstorm/tests/functional/management/__init__.py
amqpstorm/tests/functional/management/test_api.py
amqpstorm/tests/functional/management/test_basic.py
amqpstorm/tests/functional/management/test_channel.py
amqpstorm/tests/functional/management/test_connection.py
amqpstorm/tests/functional/management/test_exchange.py
amqpstorm/tests/functional/management/test_healthcheck.py
amqpstorm/tests/functional/management/test_queue.py
amqpstorm/tests/functional/management/test_user.py
amqpstorm/tests/functional/management/test_virtual_host.py
amqpstorm/tests/functional/ssl/__init__.py
amqpstorm/tests/functional/ssl/test_reliability.py
amqpstorm/tests/unit/__init__.py
amqpstorm/tests/unit/test_compatibility.py
amqpstorm/tests/unit/test_exception.py
AMQPStorm_fix-2.10.7.dist-info/LICENSE
AMQPStorm_fix-2.10.7.dist-info/METADATA
AMQPStorm_fix-2.10.7.dist-info/WHEEL
AMQPStorm_fix-2.10.7.dist-info/top_level.txt
AMQPStorm_fix-2.10.7.dist-info/RECORD
