Metadata-Version: 2.1
Name: AMQPStorm-fix
Version: 2.10.7
Summary: Thread-safe Python RabbitMQ Client & Management library.
Home-page: https://www.amqpstorm.io
Author: Erik Olof Gunnar Andersson
Author-email: me@eandersson.net
License: MIT License
Classifier: Development Status :: 5 - Production/Stable
Classifier: Intended Audience :: Developers
Classifier: License :: OSI Approved :: MIT License
Classifier: Natural Language :: English
Classifier: Operating System :: OS Independent
Classifier: Programming Language :: Python :: 2
Classifier: Programming Language :: Python :: 2.7
Classifier: Programming Language :: Python :: 3
Classifier: Programming Language :: Python :: 3.6
Classifier: Programming Language :: Python :: 3.7
Classifier: Programming Language :: Python :: 3.8
Classifier: Programming Language :: Python :: 3.9
Classifier: Programming Language :: Python :: 3.10
Classifier: Programming Language :: Python :: 3.11
Classifier: Programming Language :: Python :: 3.12
Classifier: Programming Language :: Python :: Implementation :: CPython
Classifier: Programming Language :: Python :: Implementation :: PyPy
Classifier: Topic :: Communications
Classifier: Topic :: Internet
Classifier: Topic :: Internet :: WWW/HTTP
Classifier: Topic :: Software Development :: Libraries
Classifier: Topic :: Software Development :: Libraries :: Python Modules
Classifier: Topic :: System :: Networking
Requires-Python: >=2.7
License-File: LICENSE
Requires-Dist: pamqp <3.0,>=2.0.0
Provides-Extra: management
Requires-Dist: requests >2 ; extra == 'management'
Provides-Extra: pool
Requires-Dist: amqpstorm-pool ; extra == 'pool'
